gypsum_client/__init__.py
gypsum_client/_github.py
gypsum_client/_utils.py
gypsum_client/auth.py
gypsum_client/cache_directory.py
gypsum_client/clone_operations.py
gypsum_client/config.py
gypsum_client/create_operations.py
gypsum_client/fetch_metadata_database.py
gypsum_client/fetch_metadata_schema.py
gypsum_client/fetch_operations.py
gypsum_client/list_operations.py
gypsum_client/prepare_directory_for_upload.py
gypsum_client/probation_operations.py
gypsum_client/refresh_operations.py
gypsum_client/remove_operations.py
gypsum_client/resolve_links.py
gypsum_client/rest_url.py
gypsum_client/s3_config.py
gypsum_client/save_operations.py
gypsum_client/search_metadata.py
gypsum_client/set_operations.py
gypsum_client/upload_api_operations.py
gypsum_client/upload_file_actions.py
gypsum_client/validate_metadata.py
gypsum_client-0.1.3.dist-info/LICENSE.txt
gypsum_client-0.1.3.dist-info/METADATA
gypsum_client-0.1.3.dist-info/WHEEL
gypsum_client-0.1.3.dist-info/top_level.txt
gypsum_client-0.1.3.dist-info/RECORD
