Metadata-Version: 2.1
Name: gypsum-client
Version: 0.1.3
Summary: Python client to gypsum REST API
Home-page: https://github.com/ArtifactDB/gypsum-py
Author: Jayaram Kancherla
Author-email: jayaram.kancherla@gmail.com
License: MIT
Project-URL: Documentation, https://github.com/ArtifactDB/gypsum-py
Platform: any
Classifier: Development Status :: 4 - Beta
Classifier: Programming Language :: Python
Requires-Python: >=3.8
License-File: LICENSE.txt
Requires-Dist: requests
Requires-Dist: filelock
Requires-Dist: jsonschema
Requires-Dist: importlib-metadata ; python_version < "3.8"
Provides-Extra: testing
Requires-Dist: setuptools ; extra == 'testing'
Requires-Dist: pytest ; extra == 'testing'
Requires-Dist: pytest-cov ; extra == 'testing'
